dpop/__init__.py
dpop/__main__.py
dpop/context.py
dpop/db_names.py
dpop/domain_model_db.py
dpop/exceptions.py
dpop/log.conf
dpop/metamodel_db.py
dpop/system.py
examples/ev1/EVMAN_one_bank1.sip
examples/ev1/EVMAN_types.yaml
examples/ev1/mmdb_elevator.ral
mi_domain_populate-0.1.5.dist-info/licenses/LICENSE
mi_domain_populate-0.1.5.dist-info/METADATA
mi_domain_populate-0.1.5.dist-info/WHEEL
mi_domain_populate-0.1.5.dist-info/entry_points.txt
mi_domain_populate-0.1.5.dist-info/top_level.txt
mi_domain_populate-0.1.5.dist-info/RECORD
