Metadata-Version: 2.4
Name: mi-domain-populate
Version: 0.1.5
Summary: Creates and populates a TclRAL database for a modeled domain 
Author-email: Leon Starr <leon_starr@modelint.com>
License: MIT License
Project-URL: repository, https://github.com/modelint/domain-populate
Project-URL: documentation, https://github.com/modelint/domain-populate/wiki
Keywords: shlaer-mellor,metamodel,executable uml,mbse,xuml,xtuml,platform independent,sysml
Classifier: License :: OSI Approved :: MIT License
Classifier: Programming Language :: Python
Classifier: Programming Language :: Python :: 3
Requires-Python: >=3.11
License-File: LICENSE
Requires-Dist: mi-pyral
Requires-Dist: sip-parser
Requires-Dist: PyYAML
Requires-Dist: tomli; python_version < "3.13"
Provides-Extra: build
Requires-Dist: build; extra == "build"
Requires-Dist: twine; extra == "build"
Provides-Extra: dev
Requires-Dist: bump2version; extra == "dev"
Requires-Dist: pytest; extra == "dev"
Dynamic: license-file
